PyQt4/GPL_EXCEPTION.TXT
PyQt4/GPL_EXCEPTION_ADDENDUM.TXT
PyQt4/LICENSE.GPL2
PyQt4/LICENSE.GPL3
PyQt4/OPENSOURCE-NOTICE.TXT
PyQt4/QAxContainer.pyd
PyQt4/Qsci.pyd
PyQt4/Qt.pyd
PyQt4/QtCLucene4.dll
PyQt4/QtCore.pyd
PyQt4/QtCore4.dll
PyQt4/QtDeclarative.pyd
PyQt4/QtDeclarative4.dll
PyQt4/QtDesigner.pyd
PyQt4/QtDesigner4.dll
PyQt4/QtDesignerComponents4.dll
PyQt4/QtGui.pyd
PyQt4/QtGui4.dll
PyQt4/QtHelp.pyd
PyQt4/QtHelp4.dll
PyQt4/QtMultimedia.pyd
PyQt4/QtMultimedia4.dll
PyQt4/QtNetwork.pyd
PyQt4/QtNetwork4.dll
PyQt4/QtOpenGL.pyd
PyQt4/QtOpenGL4.dll
PyQt4/QtScript.pyd
PyQt4/QtScript4.dll
PyQt4/QtScriptTools.pyd
PyQt4/QtScriptTools4.dll
PyQt4/QtSql.pyd
PyQt4/QtSql4.dll
PyQt4/QtSvg.pyd
PyQt4/QtSvg4.dll
PyQt4/QtTest.pyd
PyQt4/QtTest4.dll
PyQt4/QtWebKit.pyd
PyQt4/QtWebKit4.dll
PyQt4/QtXml.pyd
PyQt4/QtXml4.dll
PyQt4/QtXmlPatterns.pyd
PyQt4/QtXmlPatterns4.dll
PyQt4/__init__.py
PyQt4/libeay32.dll
PyQt4/libmysql.dll
PyQt4/linguist.exe
PyQt4/lrelease.exe
PyQt4/phonon.pyd
PyQt4/phonon4.dll
PyQt4/pylupdate4.exe
PyQt4/pyrcc4.exe
PyQt4/qcollectiongenerator.exe
PyQt4/qhelpgenerator.exe
PyQt4/qmake.exe
PyQt4/qscintilla2.dll
PyQt4/sip.exe
PyQt4/ssleay32.dll
PyQt4/xmlpatterns.exe
PyQt4/imports/Qt/labs/folderlistmodel/qmldir
PyQt4/imports/Qt/labs/folderlistmodel/qmlfolderlistmodelplugin.dll
PyQt4/imports/Qt/labs/gestures/qmldir
PyQt4/imports/Qt/labs/gestures/qmlgesturesplugin.dll
PyQt4/imports/Qt/labs/particles/qmldir
PyQt4/imports/Qt/labs/particles/qmlparticlesplugin.dll
PyQt4/imports/Qt/labs/shaders/qmldir
PyQt4/imports/Qt/labs/shaders/qmlshadersplugin.dll
PyQt4/imports/QtWebKit/qmldir
PyQt4/imports/QtWebKit/qmlwebkitplugin.dll
PyQt4/include/sip.h
PyQt4/plugins/accessible/qtaccessiblewidgets4.dll
PyQt4/plugins/bearer/qgenericbearer4.dll
PyQt4/plugins/bearer/qnativewifibearer4.dll
PyQt4/plugins/codecs/qcncodecs4.dll
PyQt4/plugins/codecs/qjpcodecs4.dll
PyQt4/plugins/codecs/qkrcodecs4.dll
PyQt4/plugins/codecs/qtwcodecs4.dll
PyQt4/plugins/designer/phononwidgets.dll
PyQt4_windows_whl-4.11.3.2.dist-info/WHEEL
PyQt4_windows_whl-4.11.3.2.dist-info/METADATA
PyQt4_windows_whl-4.11.3.2.dist-info/RECORD
